{"indexes":[{"v":{"$numberInt":"2"},"key":{"_id":{"$numberInt":"1"}},"name":"_id_"},{"v":{"$numberInt":"2"},"key":{"cryptocurrency":{"$numberInt":"1"},"timestamp":{"$numberInt":"1"},"granularity":{"$numberInt":"1"}},"name":"cryptocurrency_1_timestamp_1_granularity_1","unique":true},{"v":{"$numberInt":"2"},"key":{"cryptocurrency":{"$numberInt":"1"},"date":{"$numberInt":"1"},"hour":{"$numberInt":"1"},"granularity":{"$numberInt":"1"}},"name":"cryptocurrency_1_date_1_hour_1_granularity_1"},{"v":{"$numberInt":"2"},"key":{"record_id":{"$numberInt":"1"}},"name":"record_id_1","unique":true},{"v":{"$numberInt":"2"},"key":{"timestamp":{"$numberInt":"1"}},"name":"timestamp_1"},{"v":{"$numberInt":"2"},"key":{"date_only":{"$numberInt":"1"}},"name":"date_only_1"},{"v":{"$numberInt":"2"},"key":{"cryptocurrency":{"$numberInt":"1"},"timestamp":{"$numberInt":"1"}},"name":"cryptocurrency_1_timestamp_1"}],"uuid":"9329ce2b00d349db8055c8ea5802c664","collectionName":"historical_data","type":"collection"}